sensors.py
Dictsensors-0.0.1.dist-info/DESCRIPTION.rst
Dictsensors-0.0.1.dist-info/METADATA
Dictsensors-0.0.1.dist-info/RECORD
Dictsensors-0.0.1.dist-info/WHEEL
Dictsensors-0.0.1.dist-info/metadata.json
Dictsensors-0.0.1.dist-info/top_level.txt
