Metadata-Version: 2.0
Name: Dictsensors
Version: 0.0.1
Summary: Python Distribution Utilities
Home-page: https://github.com/MrS1lentcz/dictsensors
Author: Jiri Dubansky
Author-email: jiri@dubansky.cz
License: LICENSE.txt
Platform: UNKNOWN
